AUTHORS
LICENSE
MANIFEST.in
README
VERSION
setup.py
pyslid/__init__.py
pyslid/features.py
pyslid/image.py
pyslid/table.py
pyslid/utilities.py
pyslid.egg-info/PKG-INFO
pyslid.egg-info/SOURCES.txt
pyslid.egg-info/dependency_links.txt
pyslid.egg-info/requires.txt
pyslid.egg-info/top_level.txt
pyslid/database/__init__.py
pyslid/database/direct.py
pyslid/database/link.py