Metadata-Version: 1.0
Name: pyslid
Version: 0.1.0
Summary: Protein Subcellular Location Image Database for OMERO
Home-page: http://murphylab.web.cmu.edu/software/
Author: Robert F. Murphy
Author-email: murphy@cmu.edu
License: UNKNOWN
Platform: UNKNOWN
